findy/__init__.py
findy/config.json
findy/database/context.py
findy/database/persist.py
findy/database/query.py
findy/database/quote.py
findy/database/plugins/__init__.py
findy/database/plugins/recorder.py
findy/database/plugins/register.py
findy/database/plugins/baostock/__init__.py
findy/database/plugins/baostock/common.py
findy/database/plugins/baostock/meta/__init__.py
findy/database/plugins/baostock/meta/bao_china_stock_meta_recorder.py
findy/database/plugins/baostock/meta/bao_china_stock_trade_day_recorder.py
findy/database/plugins/baostock/quotes/__init__.py
findy/database/plugins/baostock/quotes/bao_china_stock_kdata_recorder.py
findy/database/plugins/eastmoney/__init__.py
findy/database/plugins/eastmoney/common.py
findy/database/plugins/eastmoney/dividend_financing/__init__.py
findy/database/plugins/eastmoney/dividend_financing/dividend_detail_recorder.py
findy/database/plugins/eastmoney/dividend_financing/dividend_financing_recorder.py
findy/database/plugins/eastmoney/dividend_financing/rights_issue_detail_recorder.py
findy/database/plugins/eastmoney/dividend_financing/spo_detail_recorder.py
findy/database/plugins/eastmoney/finance/__init__.py
findy/database/plugins/eastmoney/finance/base_china_stock_finance_recorder.py
findy/database/plugins/eastmoney/finance/china_stock_balance_sheet_recorder.py
findy/database/plugins/eastmoney/finance/china_stock_cash_flow_recorder.py
findy/database/plugins/eastmoney/finance/china_stock_finance_factor_recorder.py
findy/database/plugins/eastmoney/finance/china_stock_income_statement_recorder.py
findy/database/plugins/eastmoney/holder/__init__.py
findy/database/plugins/eastmoney/holder/top_ten_holder_recorder.py
findy/database/plugins/eastmoney/holder/top_ten_tradable_holder_recorder.py
findy/database/plugins/eastmoney/meta/__init__.py
findy/database/plugins/eastmoney/meta/china_stock_category_recorder.py
findy/database/plugins/eastmoney/meta/china_stock_meta_recorder.py
findy-0.0.2.dist-info/LICENSE
findy-0.0.2.dist-info/METADATA
findy-0.0.2.dist-info/WHEEL
findy-0.0.2.dist-info/top_level.txt
findy-0.0.2.dist-info/RECORD
